epivizfileserver/__init__.py
epivizfileserver/cli.py
epivizfileserver/client/EpivizClient.py
epivizfileserver/client/__init__.py
epivizfileserver/handler/HandlerNoActor.py
epivizfileserver/handler/__init__.py
epivizfileserver/handler/handler.py
epivizfileserver/handler/utils.py
epivizfileserver/measurements/__init__.py
epivizfileserver/measurements/measurementClass.py
epivizfileserver/measurements/measurementManager.py
epivizfileserver/parser/BamFile.py
epivizfileserver/parser/BaseFile.py
epivizfileserver/parser/BigBed.py
epivizfileserver/parser/BigWig.py
epivizfileserver/parser/GWASBigBed.py
epivizfileserver/parser/GtfFile.py
epivizfileserver/parser/GtfParsedFile.py
epivizfileserver/parser/GtfTabixFile.py
epivizfileserver/parser/HDF5File.py
epivizfileserver/parser/Helper.py
epivizfileserver/parser/InteractionBigBed.py
epivizfileserver/parser/SamFile.py
epivizfileserver/parser/TbxFile.py
epivizfileserver/parser/TileDB.py
epivizfileserver/parser/TranscriptTbxFile.py
epivizfileserver/parser/__init__.py
epivizfileserver/parser/utils.py
epivizfileserver/server/__init__.py
epivizfileserver/server/request.py
epivizfileserver/server/utils.py
epivizfileserver/tools/utils.py
epivizfileserver/trackhub/TrackHub.py
epivizfileserver/trackhub/__init__.py
epivizFileServer-0.2.7.dist-info/AUTHORS.rst
epivizFileServer-0.2.7.dist-info/LICENSE.txt
epivizFileServer-0.2.7.dist-info/METADATA
epivizFileServer-0.2.7.dist-info/WHEEL
epivizFileServer-0.2.7.dist-info/entry_points.txt
epivizFileServer-0.2.7.dist-info/top_level.txt
epivizFileServer-0.2.7.dist-info/RECORD
