Metadata-Version: 2.1
Name: epivizFileServer
Version: 0.2.7
Summary: A python library to interact, explore and compute data directly from genomic files.
Home-page: https://github.com/epiviz/epivizFileParser
Author: Jayaram Kancherla
Author-email: jayaram.kancherla@gmail.com
License: mit
Platform: any
Classifier: Intended Audience :: Developers
Classifier: Intended Audience :: Science/Research
Classifier: Natural Language :: English
Classifier: Operating System :: MacOS :: MacOS X
Classifier: Operating System :: Microsoft :: Windows
Classifier: Operating System :: POSIX :: Linux
Classifier: Programming Language :: Python :: 3
Classifier: Programming Language :: Python :: 3.6
Classifier: Programming Language :: Python :: 3.7
Classifier: Topic :: Scientific/Engineering :: Bio-Informatics
Classifier: Topic :: Scientific/Engineering :: Visualization
Requires-Dist: numpy
Requires-Dist: scipy
Requires-Dist: aiocache
Requires-Dist: dask[complete]
Requires-Dist: distributed
Requires-Dist: pandas
Requires-Dist: requests
Requires-Dist: sanic
Requires-Dist: Sanic-Cors
Requires-Dist: pysam
Requires-Dist: h5py
Requires-Dist: ujson
Requires-Dist: docopt
Requires-Dist: tqdm
Requires-Dist: tiledb
Provides-Extra: testing
Requires-Dist: pytest ; extra == 'testing'
Requires-Dist: pytest-cov ; extra == 'testing'
